{
  "$schema": "https://json-schema.org/draft/2020-12/schema",
  "$id": "https://k-comms.invalid/schemas/send-message.v1.json",
  "type": "object",
  "additionalProperties": false,
  "required": [
    "body"
  ],
  "properties": {
    "body": {
      "type": "string",
      "minLength": 1,
      "maxLength": 65535
    },
    "reply_to_message_id": {
      "type": ["string", "null"],
      "format": "uuid"
    },
    "attachment_ids": {
      "type": "array",
      "maxItems": 20,
      "uniqueItems": true,
      "items": {
        "type": "string",
        "format": "uuid"
      }
    },
    "metadata": {
      "type": "object",
      "maxProperties": 32
    }
  }
}
